{"cameraMode":{"drawMode":0,"name":"Shaded","section":"Shading Mode"},"sceneLighting":true,"audioPlay":false,"sceneViewState":{"m_AlwaysRefresh":false,"showFog":true,"showSkybox":true,"showFlares":true,"showImageEffects":true,"showParticleSystems":true,"showVisualEffectGraphs":true,"m_FxEnabled":true},"in2DMode":false,"pivot":{"x":26.28329086303711,"y":-13.903542518615723,"z":-27.121850967407228},"rotation":{"x":-0.067912757396698,"y":-0.9239565134048462,"z":0.19153498113155366,"w":-0.3245396614074707},"size":30.143699645996095,"orthographic":false}